livemark/__init__.py
livemark/__main__.py
livemark/config.py
livemark/document.py
livemark/errors.py
livemark/helpers.py
livemark/markup.py
livemark/plugin.py
livemark/project.py
livemark/server.py
livemark/settings.py
livemark/snippet.py
livemark/system.py
livemark/assets/VERSION
livemark/assets/documents/template.md
livemark/plugins/__init__.py
livemark/plugins/about/__init__.py
livemark/plugins/about/markup.html
livemark/plugins/about/plugin.py
livemark/plugins/about/style.css
livemark/plugins/audio/__init__.py
livemark/plugins/audio/base.html
livemark/plugins/audio/plugin.py
livemark/plugins/audio/soundcloud.html
livemark/plugins/audio/style.css
livemark/plugins/blog/__init__.py
livemark/plugins/blog/index.md
livemark/plugins/blog/markup.html
livemark/plugins/blog/plugin.py
livemark/plugins/blog/style.css
livemark/plugins/brand/__init__.py
livemark/plugins/brand/markup.html
livemark/plugins/brand/plugin.py
livemark/plugins/brand/style.css
livemark/plugins/cards/__init__.py
livemark/plugins/cards/markup.html
livemark/plugins/cards/plugin.py
livemark/plugins/cards/script.js
livemark/plugins/cards/style.css
livemark/plugins/chart/__init__.py
livemark/plugins/chart/markup.html
livemark/plugins/chart/plugin.py
livemark/plugins/cleanup/__init__.py
livemark/plugins/cleanup/plugin.py
livemark/plugins/columns/__init__.py
livemark/plugins/columns/markup.html
livemark/plugins/columns/plugin.py
livemark/plugins/comments/__init__.py
livemark/plugins/comments/markup.html
livemark/plugins/comments/plugin.py
livemark/plugins/comments/script.js
livemark/plugins/comments/style.css
livemark/plugins/counter/__init__.py
livemark/plugins/counter/google.html
livemark/plugins/counter/markup.html
livemark/plugins/counter/plausible.html
livemark/plugins/counter/plugin.py
livemark/plugins/display/__init__.py
livemark/plugins/display/markup.html
livemark/plugins/display/plugin.py
livemark/plugins/display/script.js
livemark/plugins/display/style.css
livemark/plugins/file/__init__.py
livemark-0.110.8.dist-info/LICENSE.md
livemark-0.110.8.dist-info/METADATA
livemark-0.110.8.dist-info/WHEEL
livemark-0.110.8.dist-info/entry_points.txt
livemark-0.110.8.dist-info/top_level.txt
livemark-0.110.8.dist-info/RECORD
